inventaire/__init__.py
inventaire/inventaire.py
inventaire/session.py
inventaire/server/__init__.py
inventaire/server/helpers.py
inventaire/server/server_api.py
inventaire/server/endpoints/__init__.py
inventaire/server/endpoints/endpoints.py
inventaire/server/endpoints/paths.py
inventaire/utils/__init__.py
inventaire/utils/common.py
inventaire_python_api-0.1.7.dist-info/LICENSE
inventaire_python_api-0.1.7.dist-info/METADATA
inventaire_python_api-0.1.7.dist-info/WHEEL
inventaire_python_api-0.1.7.dist-info/top_level.txt
inventaire_python_api-0.1.7.dist-info/RECORD
