Metadata-Version: 2.1
Name: inventaire-python-api
Version: 0.1.7
Summary: Wrappers for the Inventaire API
Home-page: https://github.com/Steinhagen/inventaire-python-api
Author: Viorel-Catalin Rapiteanu
Author-email: catalin.rapiteanu@gmail.com
Project-URL: Bug Tracker, https://github.com/Steinhagen/inventaire-python-api/issues
Classifier: Programming Language :: Python :: 3.10
Classifier: Programming Language :: Python :: 3.11
Classifier: Programming Language :: Python :: 3.12
Classifier: Programming Language :: Python :: 3.13
Classifier: License :: OSI Approved :: Apache Software License
Classifier: Operating System :: OS Independent
Requires-Python: >=3.10
License-File: LICENSE
Requires-Dist: requests
